bootcamp/week2_sequential/mod_counter/mod_counter.vhd
library IEEE;
use IEEE.STD_LOGIC_1164.ALL;
use ieee.numeric_std.all;

entity mod_counter is
	generic(N:Integer:=10);
	port(clk, reset, enable: in std_logic;
	count : out std_logic_vector(3 downto 0);
	tick  : out std_logic);
end mod_counter;

architecture lallaa of mod_counter is
	signal count_int: std_logic_vector(3 downto 0):=(others=>'0');
begin
	process (clk, reset)
	begin
		if reset = '1' then
			count_int<=(others => '0');
		elsif rising_edge(clk) then
			if enable = '1' then
				count_int<=std_logic_vector((unsigned(count_int)+1) rem N);
			end if;
		end if;
	end process;
	count <= count_int;
	tick <= '1' when unsigned(count_int) = N-1 else '0';
end lallaa;

bootcamp/week2/mod_counter/tb_mod_counter.vhd
-- the mod_counter uses the one-liner conditional to update tick

library IEEE;
use IEEE.STD_LOGIC_1164.ALL;

entity tb_mod_counter is
end tb_mod_counter;

architecture sim of tb_mod_counter is
	signal clk, reset, enable, tick:std_logic:='0';
	signal count : std_logic_vector(3 downto 0):=(others=>'0');
	signal sim_done: boolean:= false;
	constant CLK_PERIOD : time := 10 ns;
begin
	--We do not want an infinite clock!
	clk_process: process
	begin
		if sim_done then
			wait;
		end if;
		clk <= not clk;
		wait for CLK_PERIOD / 2;
	end process;

	dut: entity work.mod_counter
	port map( clk=>clk, reset=>reset, enable=>enable, tick=>tick, count=>count );

	stimulus: process
	begin
		--Part 1
		reset  <= '1';
		wait for 5 * CLK_PERIOD;

		--Part 2
		--tick shld be high for count N-1
		reset<='0';
		enable<='1';
		wait for 40*CLK_PERIOD;

		--Part 3
		enable<='0';
		wait for 5*CLK_PERIOD;

		--Part 4: restarting enable
		enable<='1';
		wait for 5*CLK_PERIOD;

		--Part 5: turn off enable and confirm that reset works
		enable<='0';
		reset<='1';
		wait for 5*CLK_PERIOD;

		--Part 6: Have you tried turning it off and on again?
		reset<='0';
		enable<='1';
		wait for 40*CLK_PERIOD;

		sim_done<=true;

		wait;

	end process;
end sim;

bootcamp/week2/mod_counter/out.vcd
$date
  Mon Jun  1 21:45:23 2026
$end
$version
  GHDL v0
$end
$timescale
  1 fs
$end
$scope module standard $end
$upscope $end
$scope module std_logic_1164 $end
$upscope $end
$scope module numeric_std $end
$upscope $end
$scope module tb_mod_counter $end
$var reg 1 ! clk $end
$var reg 1 " reset $end
$var reg 1 # enable $end
$var reg 1 $ tick $end
$var reg 4 % count[3:0] $end
$var reg 1 & sim_done $end
$scope module dut $end
$var reg 1 ' clk $end
$var reg 1 ( reset $end
$var reg 1 ) enable $end
$var reg 4 * count[3:0] $end
$var reg 1 + tick $end
$var reg 4 , count_int[3:0] $end
$upscope $end
$upscope $end
$enddefinitions $end
#0
1!
1"
0#
0$
b0000 %
0&
1'
1(
0)
b0000 *
0+
b0000 ,
#5000000
0!
0'
#10000000
1!
1'
#15000000
0!
0'
#20000000
1!
1'
#25000000
0!
0'
#30000000
1!
1'
#35000000
0!
0'
#40000000
1!
1'
#45000000
0!
0'
#50000000
1!
0"
1#
b0001 %
1'
0(
1)
b0001 *
b0001 ,
#55000000
0!
0'
#60000000
1!
b0010 %
1'
b0010 *
b0010 ,
#65000000
0!
0'
#70000000
1!
b0011 %
1'
b0011 *
b0011 ,
#75000000
0!
0'
#80000000
1!
b0100 %
1'
b0100 *
b0100 ,
#85000000
0!
0'
#90000000
1!
b0101 %
1'
b0101 *
b0101 ,
#95000000
0!
0'
#100000000
1!
b0110 %
1'
b0110 *
b0110 ,
#105000000
0!
0'
#110000000
1!
b0111 %
1'
b0111 *
b0111 ,
#115000000
0!
0'
#120000000
1!
b1000 %
1'
b1000 *
b1000 ,
#125000000
0!
0'
#130000000
1!
1$
b1001 %
1'
b1001 *
1+
b1001 ,
#135000000
0!
0'
#140000000
1!
0$
b0000 %
1'
b0000 *
0+
b0000 ,
#145000000
0!
0'
#150000000
1!
b0001 %
1'
b0001 *
b0001 ,
#155000000
0!
0'
#160000000
1!
b0010 %
1'
b0010 *
b0010 ,
#165000000
0!
0'
#170000000
1!
b0011 %
1'
b0011 *
b0011 ,
#175000000
0!
0'
#180000000
1!
b0100 %
1'
b0100 *
b0100 ,
#185000000
0!
0'
#190000000
1!
b0101 %
1'
b0101 *
b0101 ,
#195000000
0!
0'
#200000000
1!
b0110 %
1'
b0110 *
b0110 ,
#205000000
0!
0'
#210000000
1!
b0111 %
1'
b0111 *
b0111 ,
#215000000
0!
0'
#220000000
1!
b1000 %
1'
b1000 *
b1000 ,
#225000000
0!
0'
#230000000
1!
1$
b1001 %
1'
b1001 *
1+
b1001 ,
#235000000
0!
0'
#240000000
1!
0$
b0000 %
1'
b0000 *
0+
b0000 ,
#245000000
0!
0'
#250000000
1!
b0001 %
1'
b0001 *
b0001 ,
#255000000
0!
0'
#260000000
1!
b0010 %
1'
b0010 *
b0010 ,
#265000000
0!
0'
#270000000
1!
b0011 %
1'
b0011 *
b0011 ,
#275000000
0!
0'
#280000000
1!
b0100 %
1'
b0100 *
b0100 ,
#285000000
0!
0'
#290000000
1!
b0101 %
1'
b0101 *
b0101 ,
#295000000
0!
0'
#300000000
1!
b0110 %
1'
b0110 *
b0110 ,
#305000000
0!
0'
#310000000
1!
b0111 %
1'
b0111 *
b0111 ,
#315000000
0!
0'
#320000000
1!
b1000 %
1'
b1000 *
b1000 ,
#325000000
0!
0'
#330000000
1!
1$
b1001 %
1'
b1001 *
1+
b1001 ,
#335000000
0!
0'
#340000000
1!
0$
b0000 %
1'
b0000 *
0+
b0000 ,
#345000000
0!
0'
#350000000
1!
b0001 %
1'
b0001 *
b0001 ,
#355000000
0!
0'
#360000000
1!
b0010 %
1'
b0010 *
b0010 ,
#365000000
0!
0'
#370000000
1!
b0011 %
1'
b0011 *
b0011 ,
#375000000
0!
0'
#380000000
1!
b0100 %
1'
b0100 *
b0100 ,
#385000000
0!
0'
#390000000
1!
b0101 %
1'
b0101 *
b0101 ,
#395000000
0!
0'
#400000000
1!
b0110 %
1'
b0110 *
b0110 ,
#405000000
0!
0'
#410000000
1!
b0111 %
1'
b0111 *
b0111 ,
#415000000
0!
0'
#420000000
1!
b1000 %
1'
b1000 *
b1000 ,
#425000000
0!
0'
#430000000
1!
1$
b1001 %
1'
b1001 *
1+
b1001 ,
#435000000
0!
0'
#440000000
1!
0$
b0000 %
1'
b0000 *
0+
b0000 ,
#445000000
0!
0'
#450000000
1!
0#
1'
0)
#455000000
0!
0'
#460000000
1!
1'
#465000000
0!
0'
#470000000
1!
1'
#475000000
0!
0'
#480000000
1!
1'
#485000000
0!
0'
#490000000
1!
1'
#495000000
0!
0'
#500000000
1!
1#
b0001 %
1'
1)
b0001 *
b0001 ,
#505000000
0!
0'
#510000000
1!
b0010 %
1'
b0010 *
b0010 ,
#515000000
0!
0'
#520000000
1!
b0011 %
1'
b0011 *
b0011 ,
#525000000
0!
0'
#530000000
1!
b0100 %
1'
b0100 *
b0100 ,
#535000000
0!
0'
#540000000
1!
b0101 %
1'
b0101 *
b0101 ,
#545000000
0!
0'
#550000000
1!
1"
0#
b0000 %
1'
1(
0)
b0000 *
b0000 ,
#555000000
0!
0'
#560000000
1!
1'
#565000000
0!
0'
#570000000
1!
1'
#575000000
0!
0'
#580000000
1!
1'
#585000000
0!
0'
#590000000
1!
1'
#595000000
0!
0'
#600000000
1!
0"
1#
b0001 %
1'
0(
1)
b0001 *
b0001 ,
#605000000
0!
0'
#610000000
1!
b0010 %
1'
b0010 *
b0010 ,
#615000000
0!
0'
#620000000
1!
b0011 %
1'
b0011 *
b0011 ,
#625000000
0!
0'
#630000000
1!
b0100 %
1'
b0100 *
b0100 ,
#635000000
0!
0'
#640000000
1!
b0101 %
1'
b0101 *
b0101 ,
#645000000
0!
0'
#650000000
1!
b0110 %
1'
b0110 *
b0110 ,
#655000000
0!
0'
#660000000
1!
b0111 %
1'
b0111 *
b0111 ,
#665000000
0!
0'
#670000000
1!
b1000 %
1'
b1000 *
b1000 ,
#675000000
0!
0'
#680000000
1!
1$
b1001 %
1'
b1001 *
1+
b1001 ,
#685000000
0!
0'
#690000000
1!
0$
b0000 %
1'
b0000 *
0+
b0000 ,
#695000000
0!
0'
#700000000
1!
b0001 %
1'
b0001 *
b0001 ,
#705000000
0!
0'
#710000000
1!
b0010 %
1'
b0010 *
b0010 ,
#715000000
0!
0'
#720000000
1!
b0011 %
1'
b0011 *
b0011 ,
#725000000
0!
0'
#730000000
1!
b0100 %
1'
b0100 *
b0100 ,
#735000000
0!
0'
#740000000
1!
b0101 %
1'
b0101 *
b0101 ,
#745000000
0!
0'
#750000000
1!
b0110 %
1'
b0110 *
b0110 ,
#755000000
0!
0'
#760000000
1!
b0111 %
1'
b0111 *
b0111 ,
#765000000
0!
0'
#770000000
1!
b1000 %
1'
b1000 *
b1000 ,
#775000000
0!
0'
#780000000
1!
1$
b1001 %
1'
b1001 *
1+
b1001 ,
#785000000
0!
0'
#790000000
1!
0$
b0000 %
1'
b0000 *
0+
b0000 ,
#795000000
0!
0'
#800000000
1!
b0001 %
1'
b0001 *
b0001 ,
#805000000
0!
0'
#810000000
1!
b0010 %
1'
b0010 *
b0010 ,
#815000000
0!
0'
#820000000
1!
b0011 %
1'
b0011 *
b0011 ,
#825000000
0!
0'
#830000000
1!
b0100 %
1'
b0100 *
b0100 ,
#835000000
0!
0'
#840000000
1!
b0101 %
1'
b0101 *
b0101 ,
#845000000
0!
0'
#850000000
1!
b0110 %
1'
b0110 *
b0110 ,
#855000000
0!
0'
#860000000
1!
b0111 %
1'
b0111 *
b0111 ,
#865000000
0!
0'
#870000000
1!
b1000 %
1'
b1000 *
b1000 ,
#875000000
0!
0'
#880000000
1!
1$
b1001 %
1'
b1001 *
1+
b1001 ,
#885000000
0!
0'
#890000000
1!
0$
b0000 %
1'
b0000 *
0+
b0000 ,
#895000000
0!
0'
#900000000
1!
b0001 %
1'
b0001 *
b0001 ,
#905000000
0!
0'
#910000000
1!
b0010 %
1'
b0010 *
b0010 ,
#915000000
0!
0'
#920000000
1!
b0011 %
1'
b0011 *
b0011 ,
#925000000
0!
0'
#930000000
1!
b0100 %
1'
b0100 *
b0100 ,
#935000000
0!
0'
#940000000
1!
b0101 %
1'
b0101 *
b0101 ,
#945000000
0!
0'
#950000000
1!
b0110 %
1'
b0110 *
b0110 ,
#955000000
0!
0'
#960000000
1!
b0111 %
1'
b0111 *
b0111 ,
#965000000
0!
0'
#970000000
1!
b1000 %
1'
b1000 *
b1000 ,
#975000000
0!
0'
#980000000
1!
1$
b1001 %
1'
b1001 *
1+
b1001 ,
#985000000
0!
0'
#990000000
1!
0$
b0000 %
1'
b0000 *
0+
b0000 ,
#995000000
0!
0'
#1000000000
1!
b0001 %
1&
1'
b0001 *
b0001 ,
