bootcamp/week4/alu4_extended/alu4_extended.vhd
library IEEE;
use IEEE.STD_LOGIC_1164.ALL;
use IEEE.NUMERIC_STD.ALL;

entity alu4_extended is
	port (
		a		: in  std_logic_vector(3 downto 0);
		b		: in  std_logic_vector(3 downto 0);
		op	   : in  std_logic_vector(2 downto 0);
		result   : out std_logic_vector(3 downto 0);
		zero	 : out std_logic;   -- '1' when result = "0000"
		carry	: out std_logic;   -- '1' when ADD produces a carry out
		negative : out std_logic	-- '1' when result(3) = '1' (MSB set)
	);
end alu4_extended;

architecture alu of alu4_extended is
	signal result_int   : std_logic_vector(3 downto 0);
	constant ALU_ADD	: std_logic_vector(2 downto 0) := "000";
	constant ALU_SUB	: std_logic_vector(2 downto 0) := "001"; -- Carry is '0' for this operation
	constant ALU_AND	: std_logic_vector(2 downto 0) := "010";
	constant ALU_OR	 : std_logic_vector(2 downto 0) := "011";
	constant ALU_XOR	: std_logic_vector(2 downto 0) := "100";
	constant ALU_NOT	: std_logic_vector(2 downto 0) := "101";
	constant ALU_NEGATE : std_logic_vector(2 downto 0) := "110";
--  constant ALU_CLEAR  : std_logic_vector(2 downto 0) := "111";

begin
	calc: process (a, b, op)
		variable check_carry  : std_logic_vector(4 downto 0):="00000";
	begin
		result_int <= (others => '0'); -- ALU_CLEAR taken care of.
		carry <= '0';
		case op is
			when ALU_ADD =>
				result_int <= std_logic_vector(unsigned(a) + unsigned(b));
				check_carry := std_logic_vector(('0' & unsigned(a)) + ('0' & unsigned(b)));
			--  with a 4 bit check_carry
			--	if unsigned(check_carry)<unsigned(a) then
			--		carry <= '1';
			--	end if;
				carry <= check_carry(4);

			when ALU_SUB =>
				result_int <= std_logic_vector(unsigned(a)-unsigned(b));

			when ALU_AND =>
				result_int <= a and b;

			when ALU_OR =>
				result_int <= a or b;

			when ALU_XOR =>
				result_int <= a xor b;

			when ALU_NOT =>
				result_int <= not a;

			when ALU_NEGATE =>
				result_int <= std_logic_vector(-signed(a));

			when others =>
				result_int <= (others => '0');
				carry <= '0';
		end case;
	end process;

	result <= result_int;

	zero <= '0' when op="111" else '1' when result_int = "0000" else '0';
	negative <= '1' when result_int(3) = '1' else '0';
end alu;

bootcamp/week4/alu4_extended/tb_alu4_extended.vhd
library IEEE;
use IEEE.STD_LOGIC_1164.ALL;
use IEEE.NUMERIC_STD.ALL;

entity tb_alu4_extended is
end tb_alu4_extended;

architecture sim of tb_alu4_extended is

	signal a	  : std_logic_vector(3 downto 0) := (others => '0');
	signal b	  : std_logic_vector(3 downto 0) := (others => '0');
	signal op	 : std_logic_vector(2 downto 0) := (others => '0');
	signal result : std_logic_vector(3 downto 0);
	signal zero, negative, carry   : std_logic;

	constant PROP_DELAY : time := 10 ns;

begin

	uut : entity work.alu4_extended
		port map (
			a	  => a,
			b	  => b,
			op	 => op,
			result => result,
			zero   => zero,
			negative => negative,
			carry => carry
		);

	stimulus : process
	begin

		-- -------------------------------------------------------
		-- ADD  (op = "000")
		-- -------------------------------------------------------
		op <= "000";

		a <= "0011"; b <= "0101"; wait for PROP_DELAY;  -- 3+5=8
		assert result = "1000" and zero = '0' and negative = '1' and carry = '0'
			report "FAIL: ADD 3+5 => expected 1000, zero=0 and negative = '1' and carry = '0'" severity error;

		a <= "0000"; b <= "0000"; wait for PROP_DELAY;  -- 0+0=0, zero flag
		assert result = "0000" and zero = '1' and negative = '0' and carry = '0'
			report "FAIL: ADD 0+0 => expected 0000, zero=1 and negative = '0' and carry = '0'" severity error;

		a <= "1111"; b <= "0001"; wait for PROP_DELAY;  -- 15+1 wraps to 0
		assert result = "0000" and zero = '1' and negative = '0' and carry = '1'
			report "FAIL: ADD wrap 15+1 => expected 0000, zero=1 and negative = '0' and carry = '1'" severity error;

		a <= "0011"; b <= "0001"; wait for PROP_DELAY;  -- 3+1=4
		assert result = "0100" and zero = '0' and negative = '0' and carry = '0'
			report "FAIL: ADD 3+1 => expected 0100, zero=0 and negative = '0' and carry = '0'" severity error;

		-- -------------------------------------------------------
		-- SUB  (op = "001")
		-- -------------------------------------------------------
		op <= "001";

		a <= "0101"; b <= "0011"; wait for PROP_DELAY;  -- 5-3=2
		assert result = "0010" and zero = '0' and negative = '0' and carry = '0'
			report "FAIL: SUB 5-3 => expected 0010, zero=0 and negative = '0' and carry = '0'" severity error;

		a <= "0011"; b <= "0011"; wait for PROP_DELAY;  -- 3-3=0
		assert result = "0000" and zero = '1' and negative = '0' and carry = '0'
			report "FAIL: SUB 3-3 => expected 0000, zero=1 and negative = '0' and carry = '0'" severity error;

		a <= "0001"; b <= "0011"; wait for PROP_DELAY;  -- 1-3 wraps (unsigned)
		assert result = "1110" and zero = '0' and negative = '1' and carry = '0'
			report "FAIL: SUB 1-3 wrap => expected 1110, zero=0 and negative = '1' and carry = '0'" severity error;

		a <= "1011"; b <= "0011"; wait for PROP_DELAY;  -- -5-3=-8
		assert result = "1000" and zero = '0' and negative = '1' and carry = '0'
			report "FAIL: SUB 3-3 => expected 0000, zero=0 and negative = '1' and carry = '0'" severity error;

		-- -------------------------------------------------------
		-- AND  (op = "010")
		-- -------------------------------------------------------
		op <= "010";

		a <= "1100"; b <= "1010"; wait for PROP_DELAY;  -- 1100 AND 1010 = 1000
		assert result = "1000" and zero = '0' and negative = '1' and carry = '0'
			report "FAIL: AND 1100 & 1010 => expected 1000, zero=0 and negative = '1' and carry = '0'" severity error;

		a <= "1111"; b <= "0000"; wait for PROP_DELAY;  -- 1111 AND 0000 = 0000, zero
		assert result = "0000" and zero = '1' and negative = '0' and carry = '0'
			report "FAIL: AND 1111 & 0000 => expected 0000, zero=1 and negative = '0' and carry = '0'" severity error;

		-- -------------------------------------------------------
		-- OR   (op = "011")
		-- -------------------------------------------------------
		op <= "011";

		a <= "1010"; b <= "0101"; wait for PROP_DELAY;  -- 1010 OR 0101 = 1111
		assert result = "1111" and zero = '0' and negative = '1' and carry = '0'
			report "FAIL: OR 1010 | 0101 => expected 1111, zero=0 and negative = '1' and carry = '0'" severity error;

		a <= "0000"; b <= "0000"; wait for PROP_DELAY;  -- 0 OR 0 = 0
		assert result = "0000" and zero = '1' and negative = '0' and carry = '0'
			report "FAIL: OR 0|0 => expected 0000, zero=1 and negative = '0' and carry = '0'" severity error;
		-- -------------------------------------------------------
		-- XOR   (op = "100")
		-- -------------------------------------------------------
		op <= "100";

		a <= "1010"; b <= "0101"; wait for PROP_DELAY;  -- 1010 XOR 0101 = 1111
		assert result = "1111" and zero = '0' and negative = '1' and carry = '0'
			report "FAIL: XOR 1010 ^ 0101 => expected 1111, zero=1" severity error;

		a <= "0010"; b <= "0110"; wait for PROP_DELAY;  -- 0010 OR 0110 = 0100
		assert result = "0100" and zero = '0' and negative = '0' and carry = '0'
			report "FAIL: XOR 0010 ^ 0110 => expected 0100, zero=0 and negative = '0' and carry = '0'" severity error;

		-- -------------------------------------------------------
		-- NOT  (op = "101")
		-- -------------------------------------------------------
		op <= "101";

		a <= "1010"; wait for PROP_DELAY;			   -- NOT 1010 = 0101
		assert result = "0101" and zero = '0' and negative = '0' and carry = '0'
			report "FAIL: NOT 1010 => expected 0101 and zero = '0' and negative = '0' and carry = '0'" severity error;

		a <= "1111"; wait for PROP_DELAY;			   -- NOT 1111 = 0000
		assert result = "0000" and zero = '1' and negative = '0' and carry = '0'
			report "FAIL: NOT 1111 => expected 0000, zero=1 and negative = '0' and carry = '0'" severity error;

		a <= "0000"; wait for PROP_DELAY;			   -- NOT 0000 = 1111
		assert result = "1111" and zero = '0' and negative = '1' and carry = '0'
			report "FAIL: NOT 0000 => expected 1111, zero=0 and negative = '1' and carry = '0'" severity error;

		-- -------------------------------------------------------
		-- NEGATE  (op = "110")
		-- -------------------------------------------------------
		op <= "110";

		a <= "0011"; wait for PROP_DELAY;			   -- -3 = 1101
		assert result = "1101" and zero = '0' and negative = '1' and carry = '0'
			report "FAIL: NEGATE 3 => expected 1101 and zero = '0' and negative = '1' and carry = '0'" severity error;

		a <= "1010"; wait for PROP_DELAY;			   -- -(-6) = 0110
		assert result = "0110" and zero = '0' and negative = '0' and carry = '0'
			report "FAIL: NEGATE -6 => expected 0110 and zero = '0' and negative = '0' and carry = '0'" severity error;

		a <= "0000"; wait for PROP_DELAY;			   -- -0 = 0, zero flag
		assert result = "0000" and zero = '1' and negative = '0' and carry = '0'
			report "FAIL: NEGATE 0 => expected 0000, zero=1 and negative = '0' and carry = '0'" severity error;

		a <= "1000"; wait for PROP_DELAY;			   -- -(-8) = -8 (overflow)
		assert result = "1000" and zero = '0' and negative = '1' and carry = '0'
			report "FAIL: NEGATE -8 => expected 1000 (special case) and zero = '0' and negative = '1' and carry = '0'" severity error;

		-- -------------------------------------------------------
		-- Undefined (op = "111") — should output 0000
		-- -------------------------------------------------------
		op <= "111";

		a <= "1111"; b <= "1111"; wait for PROP_DELAY;
		assert result = "0000" and zero = '0' and negative = '0' and carry = '0'
			report "FAIL: undefined op 111 => expected 0000 and zero = '0' and negative = '0' and carry = '0'" severity error;

        wait for PROP_DELAY;
        report "tb_alu4: all tests complete." severity note;

		wait;
	end process;
end sim;

bootcamp/week4/alu4_extended/out.vcd
$date
  Thu Jun 11 13:12:49 2026
$end
$version
  GHDL v0
$end
$timescale
  1 fs
$end
$scope module standard $end
$upscope $end
$scope module std_logic_1164 $end
$upscope $end
$scope module numeric_std $end
$upscope $end
$scope module tb_alu4_extended $end
$var reg 4 ! a[3:0] $end
$var reg 4 " b[3:0] $end
$var reg 3 # op[2:0] $end
$var reg 4 $ result[3:0] $end
$var reg 1 % zero $end
$var reg 1 & negative $end
$var reg 1 ' carry $end
$scope module uut $end
$var reg 4 ( a[3:0] $end
$var reg 4 ) b[3:0] $end
$var reg 3 * op[2:0] $end
$var reg 4 + result[3:0] $end
$var reg 1 , zero $end
$var reg 1 - carry $end
$var reg 1 . negative $end
$var reg 4 / result_int[3:0] $end
$upscope $end
$upscope $end
$enddefinitions $end
#0
b0011 !
b0101 "
b000 #
b1000 $
0%
1&
0'
b0011 (
b0101 )
b000 *
b1000 +
0,
0-
1.
b1000 /
#10000000
b0000 !
b0000 "
b0000 $
1%
0&
b0000 (
b0000 )
b0000 +
1,
0.
b0000 /
#20000000
b1111 !
b0001 "
1'
b1111 (
b0001 )
1-
#30000000
b0011 !
b0100 $
0%
0'
b0011 (
b0100 +
0,
0-
b0100 /
#40000000
b0101 !
b0011 "
b001 #
b0010 $
b0101 (
b0011 )
b001 *
b0010 +
b0010 /
#50000000
b0011 !
b0000 $
1%
b0011 (
b0000 +
1,
b0000 /
#60000000
b0001 !
b1110 $
0%
1&
b0001 (
b1110 +
0,
1.
b1110 /
#70000000
b1011 !
b1000 $
b1011 (
b1000 +
b1000 /
#80000000
b1100 !
b1010 "
b010 #
b1100 (
b1010 )
b010 *
#90000000
b1111 !
b0000 "
b0000 $
1%
0&
b1111 (
b0000 )
b0000 +
1,
0.
b0000 /
#100000000
b1010 !
b0101 "
b011 #
b1111 $
0%
1&
b1010 (
b0101 )
b011 *
b1111 +
0,
1.
b1111 /
#110000000
b0000 !
b0000 "
b0000 $
1%
0&
b0000 (
b0000 )
b0000 +
1,
0.
b0000 /
#120000000
b1010 !
b0101 "
b100 #
b1111 $
0%
1&
b1010 (
b0101 )
b100 *
b1111 +
0,
1.
b1111 /
#130000000
b0010 !
b0110 "
b0100 $
0&
b0010 (
b0110 )
b0100 +
0.
b0100 /
#140000000
b1010 !
b101 #
b0101 $
b1010 (
b101 *
b0101 +
b0101 /
#150000000
b1111 !
b0000 $
1%
b1111 (
b0000 +
1,
b0000 /
#160000000
b0000 !
b1111 $
0%
1&
b0000 (
b1111 +
0,
1.
b1111 /
#170000000
b0011 !
b110 #
b1101 $
b0011 (
b110 *
b1101 +
b1101 /
#180000000
b1010 !
b0110 $
0&
b1010 (
b0110 +
0.
b0110 /
#190000000
b0000 !
b0000 $
1%
b0000 (
b0000 +
1,
b0000 /
#200000000
b1000 !
b1000 $
0%
1&
b1000 (
b1000 +
0,
1.
b1000 /
#210000000
b1111 !
b1111 "
b111 #
b0000 $
0&
b1111 (
b1111 )
b111 *
b0000 +
0.
b0000 /
