bootcamp/week2/counter8/counter8.vhd
library IEEE;
use IEEE.STD_LOGIC_1164.ALL;
use ieee.numeric_std.all;

entity counter8 is
    port (clk, reset, enable: in std_logic;
    count : out std_logic_vector(7 downto 0));
end counter8;

architecture count of counter8 is
    signal count_int: std_logic_vector(7 downto 0);
begin
    process (clk, reset)
    begin
        if reset = '1' then
            count_int<=(others => '0');
        elsif rising_edge(clk) then
            if enable = '1' then
                count_int<=std_logic_vector(unsigned(count_int)+1);
            end if;
        end if;
    end process;
    count <= count_int;
end count;

bootcamp/week2/counter8/tb_counter8.vhd
-- tb_counter8.vhd
--
-- Week 2 PROVIDED testbench for Exercise 1 (counter8).
--
-- You build the entity 'counter8' with the following interface:
--
--   entity counter8
--       port (
--           clk    : in  std_logic;
--           reset  : in  std_logic;
--           enable : in  std_logic;
--           count  : out std_logic_vector(7 downto 0)
--       );
--   end counter8;
--
-- This testbench drives reset, enable, and the clock so the waveform
-- shows three clearly identifiable regions:
--
--   1. an initial RESET region where count is held at 0,
--   2. a COUNTING region where enable='1' and count increments each edge,
--   3. a HOLD region where enable='0' and count stays flat.

library IEEE;
use IEEE.STD_LOGIC_1164.ALL;

entity tb_counter8 is
    -- A testbench has no ports.
end tb_counter8;

architecture sim of tb_counter8 is

    signal clk    : std_logic := '0';
    signal reset  : std_logic := '1';
    signal enable : std_logic := '0';
    signal count  : std_logic_vector(7 downto 0);

    constant CLK_PERIOD : time := 10 ns;

begin

    -- Clock generator: free-running 100 MHz square wave.
    clk <= not clk after CLK_PERIOD / 2;

    -- Instantiate the design under test.
    uut : entity work.counter8
        port map (
            clk    => clk,
            reset  => reset,
            enable => enable,
            count  => count
        );

    -- Stimulus: walk through reset -> counting -> hold.
    stimulus : process
    begin
        -- (1) RESET region: hold reset high for a few cycles.
        --     Expected in waveform: count = 0x00 throughout.
        reset  <= '1';
        enable <= '0';
        wait for 5 * CLK_PERIOD;

        -- (2) COUNTING region: release reset with enable high.
        --     Expected: count increments by 1 on each rising edge:
        --     00, 01, 02, 03, 04, 05, 06, 07, 08, 09, 0A, ...
        reset  <= '0';
        enable <= '1';
        wait for 12 * CLK_PERIOD;

        -- (3) HOLD region: lower enable, keep reset low.
        --     Expected: count stays flat at whatever value it reached.
        enable <= '0';
        wait for 6 * CLK_PERIOD;

        -- (4) Brief return to counting, just to confirm the design
        --     resumes cleanly from a hold state.
        enable <= '1';
        wait for 4 * CLK_PERIOD;

        -- End the simulation.
        --except that this doesn't do it; clock keeps switching so the process still has stuff to do as it waits
        -- I could fix the clock, but too lazy rn
        wait;
    end process;

end sim;

bootcamp/week2/counter8/out.vcd
$date
  Mon Jun  1 21:04:11 2026
$end
$version
  GHDL v0
$end
$timescale
  1 fs
$end
$scope module standard $end
$upscope $end
$scope module std_logic_1164 $end
$upscope $end
$scope module numeric_std $end
$upscope $end
$scope module tb_counter8 $end
$var reg 1 ! clk $end
$var reg 1 " reset $end
$var reg 1 # enable $end
$var reg 8 $ count[7:0] $end
$scope module uut $end
$var reg 1 % clk $end
$var reg 1 & reset $end
$var reg 1 ' enable $end
$var reg 8 ( count[7:0] $end
$var reg 8 ) count_int[7:0] $end
$upscope $end
$upscope $end
$enddefinitions $end
#0
0!
1"
0#
b00000000 $
0%
1&
0'
b00000000 (
b00000000 )
#5000000
1!
1%
#10000000
0!
0%
#15000000
1!
1%
#20000000
0!
0%
#25000000
1!
1%
#30000000
0!
0%
#35000000
1!
1%
#40000000
0!
0%
#45000000
1!
1%
#50000000
0!
0"
1#
0%
0&
1'
#55000000
1!
b00000001 $
1%
b00000001 (
b00000001 )
#60000000
0!
0%
#65000000
1!
b00000010 $
1%
b00000010 (
b00000010 )
#70000000
0!
0%
#75000000
1!
b00000011 $
1%
b00000011 (
b00000011 )
#80000000
0!
0%
#85000000
1!
b00000100 $
1%
b00000100 (
b00000100 )
#90000000
0!
0%
#95000000
1!
b00000101 $
1%
b00000101 (
b00000101 )
#100000000
0!
0%
#105000000
1!
b00000110 $
1%
b00000110 (
b00000110 )
#110000000
0!
0%
#115000000
1!
b00000111 $
1%
b00000111 (
b00000111 )
#120000000
0!
0%
#125000000
1!
b00001000 $
1%
b00001000 (
b00001000 )
#130000000
0!
0%
#135000000
1!
b00001001 $
1%
b00001001 (
b00001001 )
#140000000
0!
0%
#145000000
1!
b00001010 $
1%
b00001010 (
b00001010 )
#150000000
0!
0%
#155000000
1!
b00001011 $
1%
b00001011 (
b00001011 )
#160000000
0!
0%
#165000000
1!
b00001100 $
1%
b00001100 (
b00001100 )
#170000000
0!
0#
0%
0'
#175000000
1!
1%
#180000000
0!
0%
#185000000
1!
1%
#190000000
0!
0%
#195000000
1!
1%
#200000000
0!
0%
#205000000
1!
1%
#210000000
0!
0%
#215000000
1!
1%
#220000000
0!
0%
#225000000
1!
1%
#230000000
0!
1#
0%
1'
#235000000
1!
b00001101 $
1%
b00001101 (
b00001101 )
#240000000
0!
0%
#245000000
1!
b00001110 $
1%
b00001110 (
b00001110 )
#250000000
0!
0%
#255000000
1!
b00001111 $
1%
b00001111 (
b00001111 )
#260000000
0!
0%
#265000000
1!
b00010000 $
1%
b00010000 (
b00010000 )
