bootcamp/week3/vending_machine/vending_machine.vhd
library IEEE;
use IEEE.STD_LOGIC_1164.ALL;

entity vending_machine is
	port (
		clk	  : in  std_logic;
		reset	: in  std_logic;
		coin5	: in  std_logic;   -- '1' for one clock cycle when 5p inserted
		coin10   : in  std_logic;   -- '1' for one clock cycle when 10p inserted
		dispense : out std_logic;   -- '1' for one cycle when item is released
		change   : out std_logic	-- '1' for one cycle when 5p change is given
	);
end vending_machine;

architecture fsm of vending_machine is
	type state is (s0, s5, s10, s15, s20);
	signal current_state, next_state: state;
	signal sig5, sig10: std_logic:='0';
begin

	state_chng: process (clk)
	begin
		if rising_edge(clk) then
			if reset = '1' then
				current_state <= s0;
			else
				current_state <= next_state;
			end if;
		end if;
	end process;

	machine: process(current_state, coin5, coin10)
	begin
		next_state <= current_state;
		dispense <= '0';
		change <= '0';

		case current_state is
			when s0 =>
				if coin5='1' then
					next_state<=s5;
				elsif coin10='1' then
					next_state<=s10;
				end if;

			when s5 =>
				if coin5='1' then
					next_state<=s10;
				elsif coin10='1' then
					next_state<=s15;
				end if;

			when s10 =>
				if coin5='1' then
					next_state<=s15;
				elsif coin10='1' then
					next_state<=s20;
				end if;

			when s15 =>
				next_state<=s0;
				dispense<='1';
			--assumed here that s15 is handled sufficiently fast that user can't put a coin while vm is at s15

			when s20 =>
				next_state<=s0;
				dispense<='1';
				change<='1';
			--assumed here that s20 is handled sufficiently fast that user can't put a coin while vm is at s20

			when others =>
				next_state <= current_state;

		end case;
	end process;

end fsm;

bootcamp/week3/vending_machine/tb_vending_machine.vhd
-- tb_vending_machine.vhd
--
-- Week 3 — PROVIDED testbench for the vending_machine exercise (Exercise 1).
--
-- Covers four transaction paths:
--   (1) Three 5p coins   -> dispense, no change   (0 -> 5 -> 10 -> 15)
--   (2) One 10p + one 5p  -> dispense, no change   (0 -> 10 -> 15)
--   (3) Two 10p coins     -> dispense + change     (0 -> 10 -> 20)
--   (4) Reset mid-transaction -> credit clears, no dispense
--
-- Your vending_machine entity must use exactly these port names for the
-- instantiation below to compile.

library IEEE;
use IEEE.STD_LOGIC_1164.ALL;

entity tb_vending_machine is
end tb_vending_machine;

architecture sim of tb_vending_machine is

    signal clk      : std_logic := '0';
    signal reset    : std_logic := '1';
    signal coin5    : std_logic := '0';
    signal coin10   : std_logic := '0';
    signal dispense : std_logic;
    signal change   : std_logic;

    signal sim_done: boolean:= false;

    constant CLK_PERIOD : time := 10 ns;

    -- Pulse one coin line high for exactly one clock cycle, edge-aligned.
    -- The same helper works for either coin: pass coin5 or coin10.
    procedure insert_coin (
        signal coin    : out std_logic;
        signal clk_sig : in  std_logic
    ) is
    begin
        wait until rising_edge(clk_sig);
        coin <= '1';
        wait until rising_edge(clk_sig);
        coin <= '0';
    end procedure;

begin

    -- Clock generator
    --We do not want an infinite clock!
        clk_process: process
        begin
                if sim_done then
                        wait;
                end if;
                clk <= not clk;
                wait for CLK_PERIOD / 2;
        end process;

    -- Device under test
    uut : entity work.vending_machine
        port map (
            clk      => clk,
            reset    => reset,
            coin5    => coin5,
            coin10   => coin10,
            dispense => dispense,
            change   => change
        );

    stimulus : process
    begin

        -- ----------------------------------------------------------------
        -- Phase 0: reset
        -- ----------------------------------------------------------------
        reset <= '1';
        wait for 3 * CLK_PERIOD;
        reset <= '0';
        wait until rising_edge(clk);

        -- ----------------------------------------------------------------
        -- Phase 1: three 5p coins -> dispense (no change)
        -- Each insert_coin pulses for one cycle; one idle cycle between
        -- coins keeps the inputs cleanly separated and edge-aligned.
        -- ----------------------------------------------------------------
        insert_coin(coin5, clk);
        wait until rising_edge(clk);          -- idle cycle (no coin)
        insert_coin(coin5, clk);
        wait until rising_edge(clk);
        insert_coin(coin5, clk);
        wait for 3 * CLK_PERIOD;              -- observe dispense pulse

        -- ----------------------------------------------------------------
        -- Phase 2: reset, then 10p + 5p -> dispense (no change)
        -- ----------------------------------------------------------------
        reset <= '1';
        wait for 2 * CLK_PERIOD;
        reset <= '0';
        wait until rising_edge(clk);

        insert_coin(coin10, clk);
        wait until rising_edge(clk);
        insert_coin(coin5, clk);
        wait for 3 * CLK_PERIOD;

        -- ----------------------------------------------------------------
        -- Phase 3: reset, then 10p + 10p -> dispense + change
        -- ----------------------------------------------------------------
        reset <= '1';
        wait for 2 * CLK_PERIOD;
        reset <= '0';
        wait until rising_edge(clk);

        insert_coin(coin10, clk);
        wait until rising_edge(clk);
        insert_coin(coin10, clk);
        wait for 3 * CLK_PERIOD;

        -- ----------------------------------------------------------------
        -- Phase 4: reset mid-transaction -> no dispense
        -- Insert one 5p, then reset before the transaction completes.
        -- dispense must NOT fire afterwards.
        -- ----------------------------------------------------------------
        reset <= '1';
        wait for 2 * CLK_PERIOD;
        reset <= '0';
        wait until rising_edge(clk);

        insert_coin(coin5, clk);
        wait until rising_edge(clk);
        reset <= '1';                         -- interrupt before completion
        wait for 2 * CLK_PERIOD;
        reset <= '0';
        wait for 5 * CLK_PERIOD;              -- no more coins; no dispense

        sim_done<=true;

        wait;  -- end simulation
    end process stimulus;

end sim;

bootcamp/week3/vending_machine/out.vcd
$date
  Tue Jun  2 17:07:31 2026
$end
$version
  GHDL v0
$end
$timescale
  1 fs
$end
$scope module standard $end
$upscope $end
$scope module std_logic_1164 $end
$upscope $end
$scope module tb_vending_machine $end
$var reg 1 ! clk $end
$var reg 1 " reset $end
$var reg 1 # coin5 $end
$var reg 1 $ coin10 $end
$var reg 1 % dispense $end
$var reg 1 & change $end
$var reg 1 ' sim_done $end
$scope module uut $end
$var reg 1 ( clk $end
$var reg 1 ) reset $end
$var reg 1 * coin5 $end
$var reg 1 + coin10 $end
$var reg 1 , dispense $end
$var reg 1 - change $end
$comment current_state is not handled $end
$comment next_state is not handled $end
$var reg 1 . sig5 $end
$var reg 1 / sig10 $end
$upscope $end
$upscope $end
$enddefinitions $end
#0
1!
1"
0#
0$
0%
0&
0'
1(
1)
0*
0+
0,
0-
0.
0/
#5000000
0!
0(
#10000000
1!
1(
#15000000
0!
0(
#20000000
1!
1(
#25000000
0!
0(
#30000000
1!
0"
1(
0)
#35000000
0!
0(
#40000000
1!
1#
1(
1*
#45000000
0!
0(
#50000000
1!
0#
1(
0*
#55000000
0!
0(
#60000000
1!
1(
#65000000
0!
0(
#70000000
1!
1#
1(
1*
#75000000
0!
0(
#80000000
1!
0#
1(
0*
#85000000
0!
0(
#90000000
1!
1(
#95000000
0!
0(
#100000000
1!
1#
1(
1*
#105000000
0!
0(
#110000000
1!
0#
1%
1(
0*
1,
#115000000
0!
0(
#120000000
1!
0%
1(
0,
#125000000
0!
0(
#130000000
1!
1(
#135000000
0!
0(
#140000000
1!
1"
1(
1)
#145000000
0!
0(
#150000000
1!
1(
#155000000
0!
0(
#160000000
1!
0"
1(
0)
#165000000
0!
0(
#170000000
1!
1$
1(
1+
#175000000
0!
0(
#180000000
1!
0$
1(
0+
#185000000
0!
0(
#190000000
1!
1(
#195000000
0!
0(
#200000000
1!
1#
1(
1*
#205000000
0!
0(
#210000000
1!
0#
1%
1(
0*
1,
#215000000
0!
0(
#220000000
1!
0%
1(
0,
#225000000
0!
0(
#230000000
1!
1(
#235000000
0!
0(
#240000000
1!
1"
1(
1)
#245000000
0!
0(
#250000000
1!
1(
#255000000
0!
0(
#260000000
1!
0"
1(
0)
#265000000
0!
0(
#270000000
1!
1$
1(
1+
#275000000
0!
0(
#280000000
1!
0$
1(
0+
#285000000
0!
0(
#290000000
1!
1(
#295000000
0!
0(
#300000000
1!
1$
1(
1+
#305000000
0!
0(
#310000000
1!
0$
1%
1&
1(
0+
1,
1-
#315000000
0!
0(
#320000000
1!
0%
0&
1(
0,
0-
#325000000
0!
0(
#330000000
1!
1(
#335000000
0!
0(
#340000000
1!
1"
1(
1)
#345000000
0!
0(
#350000000
1!
1(
#355000000
0!
0(
#360000000
1!
0"
1(
0)
#365000000
0!
0(
#370000000
1!
1#
1(
1*
#375000000
0!
0(
#380000000
1!
0#
1(
0*
#385000000
0!
0(
#390000000
1!
1"
1(
1)
#395000000
0!
0(
#400000000
1!
1(
#405000000
0!
0(
#410000000
1!
0"
1(
0)
#415000000
0!
0(
#420000000
1!
1(
#425000000
0!
0(
#430000000
1!
1(
#435000000
0!
0(
#440000000
1!
1(
#445000000
0!
0(
#450000000
1!
1(
#455000000
0!
0(
#460000000
1!
1'
1(
