bootcamp/week1_basics/mux2_en/Gates.vhdl

library ieee;
use ieee.std_logic_1164.all;

package gates is

    component inverter is
        port (
            a : in std_logic;
            y : out std_logic
        );
    end component;

    component and_gate is
        port (
            a : in std_logic;
            b : in std_logic;
            y : out std_logic
        );
    end component;

    component nand_gate is
        port (
            a : in std_logic;
            b : in std_logic;
            y : out std_logic
        );
    end component;

    component or_gate is
        port (
            a : in std_logic;
            b : in std_logic;
            y : out std_logic
        );
    end component;

    component nor_gate is
        port (
            a : in std_logic;
            b : in std_logic;
            y : out std_logic
        );
    end component;

    component xor_gate is
        port (
            a : in std_logic;
            b : in std_logic;
            y : out std_logic
        );
    end component;

    component xnor_gate is
        port (
            a : in std_logic;
            b : in std_logic;
            y : out std_logic
        );
    end component;

    component half_adder is
        port (
            a     : in std_logic;
            b     : in std_logic;
            sum   : out std_logic;
            carry : out std_logic
        );
    end component;

end package gates;

--------------------------------------------------
-- Inverter
--------------------------------------------------

library ieee;
use ieee.std_logic_1164.all;

entity inverter is
    port (
        a : in std_logic;
        y : out std_logic
    );
end entity inverter;

architecture rtl of inverter is
begin

    y <= not a;

end rtl;

--------------------------------------------------
-- AND Gate
--------------------------------------------------

library ieee;
use ieee.std_logic_1164.all;

entity and_gate is
    port (
        a : in std_logic;
        b : in std_logic;
        y : out std_logic
    );
end entity and_gate;

architecture rtl of and_gate is
begin

    y <= a and b;

end rtl;

--------------------------------------------------
-- NAND Gate
--------------------------------------------------

library ieee;
use ieee.std_logic_1164.all;

entity nand_gate is
    port (
        a : in std_logic;
        b : in std_logic;
        y : out std_logic
    );
end entity nand_gate;

architecture rtl of nand_gate is
begin

    y <= not (a and b);

end rtl;

--------------------------------------------------
-- OR Gate
--------------------------------------------------

library ieee;
use ieee.std_logic_1164.all;

entity or_gate is
    port (
        a : in std_logic;
        b : in std_logic;
        y : out std_logic
    );
end entity or_gate;

architecture rtl of or_gate is
begin

    y <= a or b;

end rtl;

--------------------------------------------------
-- NOR Gate
--------------------------------------------------

library ieee;
use ieee.std_logic_1164.all;

entity nor_gate is
    port (
        a : in std_logic;
        b : in std_logic;
        y : out std_logic
    );
end entity nor_gate;

architecture rtl of nor_gate is
begin

    y <= not (a or b);

end rtl;

--------------------------------------------------
-- XOR Gate
--------------------------------------------------

library ieee;
use ieee.std_logic_1164.all;

entity xor_gate is
    port (
        a : in std_logic;
        b : in std_logic;
        y : out std_logic
    );
end entity xor_gate;

architecture rtl of xor_gate is
begin

    y <= a xor b;

end rtl;

--------------------------------------------------
-- XNOR Gate
--------------------------------------------------

library ieee;
use ieee.std_logic_1164.all;

entity xnor_gate is
    port (
        a : in std_logic;
        b : in std_logic;
        y : out std_logic
    );
end entity xnor_gate;

architecture rtl of xnor_gate is
begin

    y <= not (a xor b);

end rtl;

--------------------------------------------------
-- Half Adder
--------------------------------------------------

library ieee;
use ieee.std_logic_1164.all;

entity half_adder is
    port (
        a     : in std_logic;
        b     : in std_logic;
        sum   : out std_logic;
        carry : out std_logic
    );
end entity half_adder;

architecture rtl of half_adder is
begin

    sum   <= a xor b;
    carry <= a and b;

end rtl;

bootcamp/week1_basics/and3/and3.vhd
library IEEE;
use IEEE.STD_LOGIC_1164.ALL;

library work;
use work.gates.all;

entity and3 is
   port (a,b,c: in std_logic;
   y: out std_logic);
end and3;

architecture abc of and3 is
   signal b1: std_logic;
begin
   and1: entity work.and_gate
      port map (a=>b, b=>c, y=>b1);
   and2: entity work.and_gate
      port map (a=>a, b=>b1, y=>y);
end abc;

bootcamp/week1/and3/tb_and3.vhd
library IEEE;
use IEEE.STD_LOGIC_1164.ALL;

entity tb_and3 is
end tb_and3;

architecture sim of tb_and3 is
   signal a,b,c,y: std_logic;
begin
   dut: entity work.and3
      port map (a=>a, b=>b, c=>c, y=>y);
   stimulus: process
   begin
      a <= '0'; b <= '0'; c <= '0';
      wait for 10 ns;

      a <= '0'; b <= '0'; c <= '1';
      wait for 10 ns;

      a <= '0'; b <= '1'; c <= '0';
      wait for 10 ns;

      a <= '0'; b <= '1'; c <= '1';
      wait for 10 ns;

      a <= '1'; b <= '0'; c <= '0';
      wait for 10 ns;

      a <= '1'; b <= '0'; c <= '1';
      wait for 10 ns;

      a <= '1'; b <= '1'; c <= '0';
      wait for 10 ns;

      a <= '1'; b <= '1'; c <= '1';
      wait for 10 ns;
      
      wait;
   end process;
end sim;

bootcamp/week1_basics/and3/out.vcd
$date
  Thu May 28 17:17:19 2026
$end
$version
  GHDL v0
$end
$timescale
  1 fs
$end
$scope module standard $end
$upscope $end
$scope module std_logic_1164 $end
$upscope $end
$scope module gates $end
$upscope $end
$scope module tb_and3 $end
$var reg 1 ! a $end
$var reg 1 " b $end
$var reg 1 # c $end
$var reg 1 $ y $end
$scope module dut $end
$var reg 1 % a $end
$var reg 1 & b $end
$var reg 1 ' c $end
$var reg 1 ( y $end
$var reg 1 ) b1 $end
$scope module and1 $end
$var reg 1 * a $end
$var reg 1 + b $end
$var reg 1 , y $end
$upscope $end
$scope module and2 $end
$var reg 1 - a $end
$var reg 1 . b $end
$var reg 1 / y $end
$upscope $end
$upscope $end
$upscope $end
$enddefinitions $end
#0
0!
0"
0#
0$
0%
0&
0'
0(
0)
0*
0+
0,
0-
0.
0/
#10000000
1#
1'
1+
#20000000
1"
0#
1&
0'
1*
0+
#30000000
1#
1'
1)
1+
1,
1.
#40000000
1!
0"
0#
0$
1%
0&
0'
0(
0)
0*
0+
0,
1-
0.
0/
#50000000
1#
1'
1+
#60000000
1"
0#
1&
0'
1*
0+
#70000000
1#
1$
1'
1(
1)
1+
1,
1.
1/
