bootcamp/week4/ram8x8/ram8x8.vhd
library IEEE;
use IEEE.STD_LOGIC_1164.ALL;
use IEEE.NUMERIC_STD.ALL;

entity ram8x8 is
	port (
		clk	   : in  std_logic;
		we		: in  std_logic;					 -- write enable
		reset : in std_logic;
		addr	  : in  std_logic_vector(2 downto 0);  -- 3-bit address (0..7)
		data_in   : in  std_logic_vector(7 downto 0);  -- write data
		data_out  : out std_logic_vector(7 downto 0);  -- read data
		valid	 : out std_logic					   -- '1' one cycle after read
	);
end ram8x8;

architecture rw of ram8x8 is
	type ram_type is array (0 to 7) of std_logic_vector(7 downto 0);
	signal ram_mem : ram_type := (others => (others => '0')); -- (others => "00000000" also works; but the size of each elem of ram is hard-coded this way, which I guess one would not want
begin
	process (clk)
	begin
		if rising_edge(clk) then
			if reset='1' then
				data_out <= (others => '0');
				valid<='0';
			else
				if we = '1' then
					-- WRITE: store data_bus into addressed location.
					-- RAM does not drive the bus during a write (data is incoming).
					ram_mem(to_integer(unsigned(addr))) <= data_in;
					valid <= '0';
				else
					-- READ: capture addressed location into output register.
					data_out <= ram_mem(to_integer(unsigned(addr)));
					valid  <= '1';
				end if;
			end if;
		end if;
	end process;
end rw;

bootcamp/week4/ram8x8/tb_ram8x8.vhd
library IEEE;
use IEEE.STD_LOGIC_1164.ALL;

entity tb_ram8x8 is
end tb_ram8x8;

architecture sim of tb_ram8x8 is

	signal clk	  : std_logic := '0';
	signal reset	: std_logic := '1';
	signal we	   : std_logic := '0';
	signal addr	 : std_logic_vector(2 downto 0) := (others => '0');
	signal data_in  : std_logic_vector(7 downto 0) := (others => '0');
	signal data_out : std_logic_vector(7 downto 0);
	signal valid	: std_logic;

	signal sim_done: boolean:= false;

	constant CLK_PERIOD : time := 10 ns;

begin

	-- Clock generator
	--We do not want an infinite clock!
		clk_process: process
		begin
				if sim_done then
						wait;
				end if;
				clk <= not clk;
				wait for CLK_PERIOD / 2;
		end process;

	uut : entity work.ram8x8
		port map (
			clk	  => clk,
			we	   => we,
			reset	 => reset,
			addr	 => addr,
			data_in  => data_in,
			data_out => data_out,
			valid	=> valid
		);

	stimulus : process
	begin

		-- Phase 1: Reset (Needs to be tested later, obviously, but I'll let this section stay)
		reset <= '1';
		wait until rising_edge(clk);
		wait until rising_edge(clk);
		reset <= '0';
		wait until rising_edge(clk);

		-- Phase 2: Write four values
		-- Write 0xAA → address 0
		wait until rising_edge(clk);
		we <= '1'; addr <= "000"; data_in <= x"AA";

		-- Write 0xBB → address 1
		wait until rising_edge(clk);
		addr <= "001"; data_in <= x"BB";

		-- Write 0xCC → address 2
		wait until rising_edge(clk);
		addr <= "010"; data_in <= x"CC";

		-- Write 0xDD → address 3
		wait until rising_edge(clk);
		addr <= "011"; data_in <= x"DD";

		-- Phase 3: Read back all four values (check valid timing)
		wait until rising_edge(clk);
		we <= '0'; addr <= "000";  -- read address 0

		wait until rising_edge(clk);  -- data_out now holds 0xAA, valid='1'
		wait for 1 fs;
		assert data_out = x"AA" and valid = '1'
			report "FAIL: read addr 0" severity error;

		addr <= "001";				-- read address 1
		wait until rising_edge(clk);
		wait for 1 fs;
		assert data_out = x"BB" and valid = '1'
			report "FAIL: read addr 1" severity error;

		addr <= "010";
		wait until rising_edge(clk);
		wait for 1 fs;
		assert data_out = x"CC" report "FAIL: read addr 2" severity error;

		addr <= "011";
		wait until rising_edge(clk);
		wait for 1 fs;
		assert data_out = x"DD" report "FAIL: read addr 3" severity error;

		addr <= "010";
		reset<='1';
		wait until rising_edge(clk);
		wait for 1 fs;
		assert data_out = x"00" report "FAIL: read addr 2 after reset" severity error;
		reset<='0';

		-- Phase 4: Overwrite address 0 and verify updated value
		wait until rising_edge(clk);
		wait for 1 fs;
		we <= '1'; addr <= "000"; data_in <= x"FF";

		wait until rising_edge(clk);
		wait for 1 fs;
		we <= '0'; addr <= "000";

		wait until rising_edge(clk);
		wait for 1 fs;
		assert data_out = x"FF"
			report "FAIL: read after overwrite addr 0" severity error;

		-- Phase 5: Check valid is '0' in a write cycle
		wait until rising_edge(clk);
		we <= '1'; addr <= "000"; data_in <= x"11";
		wait until rising_edge(clk);
		wait for 1 fs;
		assert valid = '0'
			report "FAIL: valid should be '0' after write" severity error;
		
		-- Phase 6: valid = '1' in a read cycle
		wait until rising_edge(clk);
		we <= '0'; addr <= "000";
		wait until rising_edge(clk);
		wait for 1 fs;
		assert valid = '1'
			report "FAIL: valid should be '1' after read" severity error;

		wait until rising_edge(clk);
		report "RAM testbench complete." severity note;
		sim_done <= true;
		wait;
	end process stimulus;

end sim;

bootcamp/week4/ram8x8/out.vcd
$date
  Mon Jun 22 17:17:07 2026
$end
$version
  GHDL v0
$end
$timescale
  1 fs
$end
$scope module standard $end
$upscope $end
$scope module std_logic_1164 $end
$upscope $end
$scope module numeric_std $end
$upscope $end
$scope module tb_ram8x8 $end
$var reg 1 ! clk $end
$var reg 1 " reset $end
$var reg 1 # we $end
$var reg 3 $ addr[2:0] $end
$var reg 8 % data_in[7:0] $end
$var reg 8 & data_out[7:0] $end
$var reg 1 ' valid $end
$var reg 1 ( sim_done $end
$scope module uut $end
$var reg 1 ) clk $end
$var reg 1 * we $end
$var reg 1 + reset $end
$var reg 3 , addr[2:0] $end
$var reg 8 - data_in[7:0] $end
$var reg 8 . data_out[7:0] $end
$var reg 1 / valid $end
$comment ram_mem is not handled $end
$upscope $end
$upscope $end
$enddefinitions $end
#0
1!
1"
0#
b000 $
b00000000 %
b00000000 &
0'
0(
1)
0*
1+
b000 ,
b00000000 -
b00000000 .
0/
#5000000
0!
0)
#10000000
1!
0"
1)
0+
#15000000
0!
0)
#20000000
1!
1'
1)
1/
#25000000
0!
0)
#30000000
1!
1#
b10101010 %
1)
1*
b10101010 -
#35000000
0!
0)
#40000000
1!
b001 $
b10111011 %
0'
1)
b001 ,
b10111011 -
0/
#45000000
0!
0)
#50000000
1!
b010 $
b11001100 %
1)
b010 ,
b11001100 -
#55000000
0!
0)
#60000000
1!
b011 $
b11011101 %
1)
b011 ,
b11011101 -
#65000000
0!
0)
#70000000
1!
0#
b000 $
1)
0*
b000 ,
#75000000
0!
0)
#80000000
1!
b10101010 &
1'
1)
b10101010 .
1/
#80000001
b001 $
b001 ,
#85000000
0!
0)
#90000000
1!
b10111011 &
1)
b10111011 .
#90000001
b010 $
b010 ,
#95000000
0!
0)
#100000000
1!
b11001100 &
1)
b11001100 .
#100000001
b011 $
b011 ,
#105000000
0!
0)
#110000000
1!
b11011101 &
1)
b11011101 .
#110000001
1"
b010 $
1+
b010 ,
#115000000
0!
0)
#120000000
1!
b00000000 &
0'
1)
b00000000 .
0/
#120000001
0"
0+
#125000000
0!
0)
#130000000
1!
b11001100 &
1'
1)
b11001100 .
1/
#130000001
1#
b000 $
b11111111 %
1*
b000 ,
b11111111 -
#135000000
0!
0)
#140000000
1!
0'
1)
0/
#140000001
0#
0*
#145000000
0!
0)
#150000000
1!
b11111111 &
1'
1)
b11111111 .
1/
#155000000
0!
0)
#160000000
1!
1#
b00010001 %
1)
1*
b00010001 -
#165000000
0!
0)
#170000000
1!
0'
1)
0/
#175000000
0!
0)
#180000000
1!
0#
1)
0*
#185000000
0!
0)
#190000000
1!
b00010001 &
1'
1)
b00010001 .
1/
#195000000
0!
0)
#200000000
1!
1(
1)
