bootcamp/week3/seq_det_101_nonoverlap/seq_det_101_nonoverlap.vhd
library IEEE;
use IEEE.STD_LOGIC_1164.ALL;

entity seq_det_101_nonoverlap is
    port (
        clk      : in  std_logic;
        reset    : in  std_logic;
        data     : in  std_logic;
        detected : out std_logic
    );
end seq_det_101_nonoverlap;

architecture fsm of seq_det_101_nonoverlap is
	type state is (s, s1, s10, s101);
	signal current_state, next_state: state;
begin
	state_chng: process (clk)
	begin
		if rising_edge(clk) then
			if reset = '1' then
				current_state<=s;
			else
				current_state <= next_state;
			end if;
		end if;
	end process;

	machine: process(current_state, data)
	begin
		next_state <= current_state;
		detected <='0';

		case current_state is
			when s =>
				if data='1' then next_state <= s1; else next_state <= s; end if;

			when s1 =>
				if data='0' then next_state <= s10; elsif data='1' then next_state <= s1; else next_state<=s; end if; --Beware of undefined
				--Resetting at unkown signal in above

			when s10 =>
				if data='1' then next_state <= s101; else next_state <= s; end if;

			when s101 =>
				detected <='1';
				if data='1' then next_state <= s1; else next_state <= s; end if;

			when others =>
				next_state <= current_state;
		end case;
	end process;

end fsm;

bootcamp/week3/seq_det_101_nonoverlap/tb_seq_det_101_nonoverlap.vhd
library IEEE;
use IEEE.STD_LOGIC_1164.ALL;

entity tb_seq_det_101_nonoverlap is
end tb_seq_det_101_nonoverlap;

architecture sim of tb_seq_det_101_nonoverlap is
	signal clk, data, detected: std_logic:='0';
	signal reset: std_logic:='1';
	signal sim_done: boolean:= false;
	constant CLK_PERIOD : time := 10 ns;
begin
	-- Clock generator
	--We do not want an infinite clock!
		clk_process: process
		begin
				if sim_done then
						wait;
				end if;
				clk <= not clk;
				wait for CLK_PERIOD / 2;
		end process;
	-- Device under test
	uut : entity work.seq_det_101_nonoverlap
		port map (
			clk	  => clk,
			reset	=> reset,
			data	 => data,
			detected => detected
		);

	stimulus : process
	begin
		-- PART 1
		reset <= '1';
		wait for 3 * CLK_PERIOD;
		reset <= '0';
		-- Important to test reset when the state differs from initial state; TODO

		-- PART 2: testing pattern 10101
		wait until rising_edge(clk); data <= '1';
		wait until rising_edge(clk); data <= '0';
		wait until rising_edge(clk); data <= '1';
		wait until rising_edge(clk); data <= '0';
		wait until rising_edge(clk); data <= '1';
		wait until rising_edge(clk);
		-- Expected state: s1

		--PART 3: TODO of PART 1
		reset <= '1';
		wait until rising_edge(clk); data <= '0';
		wait until rising_edge(clk);
		reset <= '0';
		data <= '1'; -- If reset fails but counter works, then detected will be '1' here; observed in next cycle
		wait until rising_edge(clk); data <= '0';
		wait until rising_edge(clk); data <= '1'; -- If everything works nicely, detected will be '1' here; observed in next cycle
		wait until rising_edge(clk); data <= '0';
		wait until rising_edge(clk);

		-- PART 4: end stimulus
		sim_done<=true;
		wait;
	end process;
end sim;

bootcamp/week3/seq_det_101_nonoverlap/out.vcd
$date
  Tue Jun  2 18:50:47 2026
$end
$version
  GHDL v0
$end
$timescale
  1 fs
$end
$scope module standard $end
$upscope $end
$scope module std_logic_1164 $end
$upscope $end
$scope module tb_seq_det_101_nonoverlap $end
$var reg 1 ! clk $end
$var reg 1 " data $end
$var reg 1 # detected $end
$var reg 1 $ reset $end
$var reg 1 % sim_done $end
$scope module uut $end
$var reg 1 & clk $end
$var reg 1 ' reset $end
$var reg 1 ( data $end
$var reg 1 ) detected $end
$comment current_state is not handled $end
$comment next_state is not handled $end
$upscope $end
$upscope $end
$enddefinitions $end
#0
1!
0"
0#
1$
0%
1&
1'
0(
0)
#5000000
0!
0&
#10000000
1!
1&
#15000000
0!
0&
#20000000
1!
1&
#25000000
0!
0&
#30000000
1!
1"
0$
1&
0'
1(
#35000000
0!
0&
#40000000
1!
0"
1&
0(
#45000000
0!
0&
#50000000
1!
1"
1&
1(
#55000000
0!
0&
#60000000
1!
0"
1#
1&
0(
1)
#65000000
0!
0&
#70000000
1!
1"
0#
1&
1(
0)
#75000000
0!
0&
#80000000
1!
1$
1&
1'
#85000000
0!
0&
#90000000
1!
0"
1&
0(
#95000000
0!
0&
#100000000
1!
1"
0$
1&
0'
1(
#105000000
0!
0&
#110000000
1!
0"
1&
0(
#115000000
0!
0&
#120000000
1!
1"
1&
1(
#125000000
0!
0&
#130000000
1!
0"
1#
1&
0(
1)
#135000000
0!
0&
#140000000
1!
0#
1%
1&
0)
