bootcamp/week5/exercise_1/alu8.vhd
-- alu8.vhd
--
-- Week 5 — PROVIDED 8-bit ALU for the mini-datapath.
-- Do NOT modify this file.
--
-- Operation table:
--   "000"  ADD     result = a + b
--   "001"  SUB     result = a - b
--   "010"  AND     result = a AND b (bitwise)
--   "011"  OR      result = a OR b  (bitwise)
--   "100"  NOT     result = NOT a   (b ignored)
--   "101"  NEGATE  result = -a      (b ignored, two's complement)
--   "110"  XOR     result = a XOR b (bitwise)
--   "111"  PASS    result = b       (used for LOAD instruction)
--   others          result = 0x00

library IEEE;
use IEEE.STD_LOGIC_1164.ALL;
use IEEE.NUMERIC_STD.ALL;

entity alu8 is
    port (
        a      : in  std_logic_vector(7 downto 0);
        b      : in  std_logic_vector(7 downto 0);
        op     : in  std_logic_vector(2 downto 0);
        result : out std_logic_vector(7 downto 0);
        zero   : out std_logic
    );
end alu8;

architecture rtl of alu8 is

    signal result_int : std_logic_vector(7 downto 0);

begin

    alu_proc : process (a, b, op)
    begin
        result_int <= (others => '0');

        case op is
            when "000" =>   -- ADD
                result_int <= std_logic_vector(unsigned(a) + unsigned(b));

            when "001" =>   -- SUB
                result_int <= std_logic_vector(unsigned(a) - unsigned(b));

            when "010" =>   -- AND
                result_int <= a and b;

            when "011" =>   -- OR
                result_int <= a or b;

            when "100" =>   -- NOT a
                result_int <= not a;

            when "101" =>   -- NEGATE a
                result_int <= std_logic_vector(-signed(a));

            when "110" =>   -- XOR
                result_int <= a xor b;

            when "111" =>   -- PASS: output = b
                -- Used by LOAD instruction to move mem_data_out into acc
                -- without any arithmetic.
                result_int <= b;

            when others =>
                result_int <= (others => '0');
        end case;
    end process alu_proc;

    result <= result_int;
    zero   <= '1' when result_int = x"00" else '0';

end rtl;

bootcamp/week5/exercise_1/ram32x8.vhd
-- ram32x8.vhd
--
-- Week 5 — PROVIDED 32-location × 8-bit synchronous RAM.
--
-- Edit the section marked "PROGRAM: edit this initialiser" to load
-- your program and data for each exercise.
--
-- Port summary:
--   clk	  : in  std_logic
--   we	   : in  std_logic		 -- '1' = write, '0' = read
--   addr	 : in  std_logic_vector(4 downto 0)   -- 5-bit address (0..31)
--   data_in  : in  std_logic_vector(7 downto 0)   -- write data
--   data_out : out std_logic_vector(7 downto 0)   -- read data (1-cycle latency)
--
-- Behaviour:
--   Write: on rising_edge(clk) with we='1', data_in is stored at addr.
--   Read:  on rising_edge(clk) with we='0', ram(addr) is captured into
--		  data_out register. Data appears on data_out the NEXT clock cycle.

library IEEE;
use IEEE.STD_LOGIC_1164.ALL;
use IEEE.NUMERIC_STD.ALL;

entity ram32x8 is
	port (
		clk	  : in  std_logic;
		we	   : in  std_logic;
		addr	 : in  std_logic_vector(4 downto 0);
		data_in  : in  std_logic_vector(7 downto 0);
		data_out : out std_logic_vector(7 downto 0)
	);
end ram32x8;

architecture rtl of ram32x8 is

	type ram_type is array (0 to 31) of std_logic_vector(7 downto 0);

	-- ==============================================================
	-- PROGRAM: edit this initialiser for each exercise.
	--
	-- Instruction encoding:
	--   bits[7:5] = opcode:  000=LOAD  001=ADD  010=STORE  011=HALT
	--   bits[4:0] = operand address (decimal index into this array)
	--
	-- Array indices are DECIMAL. Address 0x10 = index 16, etc.
	--
	-- Example (Program 1: result = 7 + 5, stored at address 18):
	--   0  => "00010000",  -- LOAD  addr 16  (000 10000)
	--   1  => "00110001",  -- ADD   addr 17  (001 10001)
	--   2  => "01010010",  -- STORE addr 18  (010 10010)
	--   3  => "01100000",  -- HALT		   (011 00000)
	--   16 => "00000111",  -- data: A = 7
	--   17 => "00000101",  -- data: B = 5
	--   18 => "00000000",  -- result placeholder
	-- ==============================================================
	signal ram_mem : ram_type := (
		-- TODO: replace this placeholder with your encoded program.
		-- I like hexadecimal
		-- Instructions go at low addresses (0, 1, 2, 3, ...)
		16#00# => x"10", -- LOAD 0x10
		16#01# => x"31", -- ADD 0x11
		16#02# => x"32", -- ADD 0x12
		16#03# => x"53", -- STORE 0x13
		16#04# => x"60", -- HALT
		-- Data goes at higher addresses (16, 17, 18, ...)
		16#10# => x"0F", -- A
		16#11# => x"09", -- B
		16#12# => x"FC", -- C
		others => (others => '0')
	);

	signal data_out_reg : std_logic_vector(7 downto 0) := (others => '0');

begin

	mem_proc : process (clk)
	begin
		if rising_edge(clk) then
			if we = '1' then
				ram_mem(to_integer(unsigned(addr))) <= data_in;
			end if;
			-- Read: always register the output (1-cycle latency)
			data_out_reg <= ram_mem(to_integer(unsigned(addr)));
		end if;
	end process mem_proc;

	data_out <= data_out_reg;

end rtl;

bootcamp/week5/exercise_1/mini_cpu.vhd
library IEEE;
use IEEE.STD_LOGIC_1164.ALL;
use IEEE.NUMERIC_STD.ALL;

entity mini_cpu is
	port (
		clk   : in  std_logic;
		reset : in  std_logic;
		done  : out std_logic;
		dbg_acc:   out std_logic_vector(7 downto 0);
		dbg_pc:    out std_logic_vector(4 downto 0);
		dbg_ir:    out std_logic_vector(7 downto 0);
		dbg_state: out std_logic_vector(2 downto 0)
	);
end mini_cpu;

architecture rtl of mini_cpu is

	type state_type is (S_FETCH1, S_FETCH2, S_EXECUTE, S_WRITEBACK, S_HALT);
	signal state	  : state_type := S_FETCH1;
	signal next_state : state_type;

	signal pc	  : unsigned(4 downto 0) := (others => '0'); 
	signal ir	  : std_logic_vector(7 downto 0) := (others => '0'); 
	signal acc	 : std_logic_vector(7 downto 0) := (others => '0'); 

	signal ir_opcode   : std_logic_vector(2 downto 0); 
	signal ir_operand  : std_logic_vector(4 downto 0); 
	signal addr		: std_logic_vector(4 downto 0); 
	signal alu_result  : std_logic_vector(7 downto 0);
	signal alu_zero	: std_logic;
	signal mem_data_out: std_logic_vector(7 downto 0);

	signal alu_op   : std_logic_vector(2 downto 0);
	signal acc_ld   : std_logic;
	signal ir_ld	: std_logic;
	signal mem_we   : std_logic;
	signal pc_inc   : std_logic;
	signal addr_sel : std_logic;
	signal done_int : std_logic;

	constant OP_LOAD  : std_logic_vector(2 downto 0) := "000";
	constant OP_ADD   : std_logic_vector(2 downto 0) := "001";
	constant OP_STORE : std_logic_vector(2 downto 0) := "010";
	constant OP_HALT  : std_logic_vector(2 downto 0) := "011";

	constant ALU_ADD  : std_logic_vector(2 downto 0) := "000";
	constant ALU_PASS : std_logic_vector(2 downto 0) := "111"; 

begin

	ir_opcode  <= ir(7 downto 5);
	ir_operand <= ir(4 downto 0);

	addr <= std_logic_vector(pc) when addr_sel = '0'
			else ir_operand;

	ram_inst : entity work.ram32x8
		port map (
			clk	  => clk,
			we	   => mem_we,
			addr	 => addr,
			data_in  => acc,
			data_out => mem_data_out
		);

	alu_inst : entity work.alu8
		port map (
			a	  => acc,
			b	  => mem_data_out,
			op	 => alu_op,
			result => alu_result,
			zero   => alu_zero
		);

	registers : process (clk)
	begin
		if rising_edge(clk) then
			if reset = '1' then
				state <= S_FETCH1;
				pc	<= (others => '0');
				ir	<= (others => '0');
				acc   <= (others => '0');
			else
				state <= next_state;

				if pc_inc = '1' then
					pc <= pc + 1;
				end if;

				if ir_ld = '1' then
					ir <= mem_data_out;
				end if;

				if acc_ld = '1' then
					acc <= alu_result;
				end if;
			end if;
		end if;
	end process registers;

	control : process (state, ir_opcode)
	begin
		next_state <= state;		  
		alu_op	 <= ALU_PASS;
		acc_ld	 <= '0';
		ir_ld	  <= '0';
		mem_we	 <= '0';
		pc_inc	 <= '0';
		addr_sel   <= '0';
		done_int   <= '0';

		case state is

			when S_FETCH1 =>
				addr_sel   <= '0';	
				next_state <= S_FETCH2;

			when S_FETCH2 =>
				addr_sel   <= '0';	
				ir_ld	  <= '1';	
				pc_inc	 <= '1';	
				next_state <= S_EXECUTE;

			when S_EXECUTE =>
				addr_sel <= '1';	  

				case ir_opcode is
					when OP_LOAD | OP_ADD | OP_STORE =>
						next_state <= S_WRITEBACK;
					when OP_HALT =>
						next_state <= S_HALT;
					when others =>
						next_state <= S_FETCH1;
				end case;

			when S_WRITEBACK =>
				addr_sel <= '1';	   

				case ir_opcode is
					when OP_LOAD =>
						alu_op	 <= ALU_PASS;
						acc_ld	 <= '1';
						next_state <= S_FETCH1;

					when OP_ADD =>
						alu_op	 <= ALU_ADD;
						acc_ld	 <= '1';
						next_state <= S_FETCH1;

					when OP_STORE =>
						mem_we	 <= '1';
						next_state <= S_FETCH1;

					when others =>
						next_state <= S_FETCH1;
				end case;

			when S_HALT =>
				done_int   <= '1';
				next_state <= S_HALT;   

			when others =>
				next_state <= S_FETCH1;

		end case;
	end process control;

	dbg_acc   <= acc;
	dbg_pc    <= std_logic_vector(pc);
	dbg_ir    <= ir;
	dbg_state <= "000" when state = S_FETCH1
	        else "001" when state = S_FETCH2
	        else "010" when state = S_EXECUTE
	        else "011" when state = S_WRITEBACK
	        else "100"; -- S_HALT

	done <= done_int;

end rtl;

bootcamp/week5/exercise_1/tb_mini_cpu_ex1.vhd
-- tb_template_datapath.vhd
--
-- Week 5 STARTER TEMPLATE for mini_cpu testbenches.
--
-- Copy this file, rename it (e.g. tb_mini_cpu_ex1.vhd), then:
--   1. Rename the entity to match your file (e.g. tb_mini_cpu_ex1).
--   2. Fill in the port map with the debug signals from your mini_cpu.
--   3. Replace the TODO assert blocks with your expected values.
--
-- Pre-written for you:
--   - Clock generator
--   - Reset phase (3 cycles)
--   - wait until done with 30-cycle timeout
--   - Reset recovery check

library IEEE;
use IEEE.STD_LOGIC_1164.ALL;
use IEEE.NUMERIC_STD.ALL;

-- TODO: rename this entity to match your file name
entity tb_mini_cpu_ex1 is
end tb_mini_cpu_ex1;

architecture sim of tb_mini_cpu_ex1 is

	signal clk	   : std_logic := '0';
	signal reset	 : std_logic := '1';
	signal done	  : std_logic;

	-- Debug signals: uncomment and add more as needed.
	-- These must match the debug ports you added to mini_cpu.vhd.
	signal dbg_acc   : std_logic_vector(7 downto 0);
	signal dbg_pc	: std_logic_vector(4 downto 0);
	signal dbg_ir	: std_logic_vector(7 downto 0);
	signal dbg_state : std_logic_vector(2 downto 0);
	--   "000"=S_FETCH1, "001"=S_FETCH2, "010"=S_EXECUTE, "011"=S_WRITEBACK, "100"=S_HALT

	signal sim_done: boolean:= false;

	constant CLK_PERIOD : time := 10 ns;

begin

	-- Clock generator
	--We do not want an infinite clock!
		clk_process: process
		begin
				if sim_done then
						wait;
				end if;
				clk <= not clk;
				wait for CLK_PERIOD / 2;
		end process;

	-- DUT instantiation
	-- TODO: replace 'mini_cpu' with your actual entity name if different,
	--	   and update the port map to match your debug port names.
	uut : entity work.mini_cpu
		port map (
			clk	   => clk,
			reset	 => reset,
			done	  => done,
			dbg_acc   => dbg_acc,
			dbg_pc	=> dbg_pc,
			dbg_ir	=> dbg_ir,
			dbg_state => dbg_state
		);

	stimulus : process
	begin

		-- -------------------------------------------------------
		-- Phase 1: Apply reset for 3 cycles
		-- -------------------------------------------------------
		reset <= '1';
		wait for 3 * CLK_PERIOD;
		reset <= '0';

		-- -------------------------------------------------------
		-- Phase 2: Wait for program to complete (30-cycle timeout)
		-- -------------------------------------------------------
		wait until done = '1' for 30 * CLK_PERIOD;

		assert done = '1'
			report "FAIL: done never asserted - CPU did not reach HALT " &
				   "(check FSM, HALT opcode, and RAM initialiser)"
			severity error;

		-- Allow one more cycle to settle after done goes high
		wait for CLK_PERIOD;

		-- -------------------------------------------------------
		-- Phase 3: Check final state
		-- TODO: replace x"??" with your expected final acc value.
		-- TODO: replace "?????" with your expected final PC value (binary).
		-- -------------------------------------------------------
		assert dbg_acc = x"14"
			report "FAIL: acc has wrong final value"
			severity error;

		assert dbg_pc = "00101"
			report "FAIL: PC not frozen at expected HALT address"
			severity error;

		assert dbg_state = "100"
			report "FAIL: CPU not in HALT state (expected state=100)"
			severity error;

		-- -------------------------------------------------------
		-- Phase 4: Verify CPU stays in HALT (does not escape)
		-- -------------------------------------------------------
		wait for 5 * CLK_PERIOD;

		assert done = '1'
			report "FAIL: CPU escaped HALT state"
			severity error;

		assert dbg_acc = x"14"
			report "FAIL: acc changed while in HALT"
			severity error;

		-- -------------------------------------------------------
		-- Phase 5: Reset recovery - CPU must return to FETCH at PC=0
		-- -------------------------------------------------------
		reset <= '1';
		wait for 2 * CLK_PERIOD;
		reset <= '0';
		wait for CLK_PERIOD;

		assert dbg_pc = "00000"
			report "FAIL: PC should be 0 after reset"
			severity error;

		assert done = '0'
			report "FAIL: done should be '0' after reset"
			severity error;

		assert dbg_state = "001"
			report "FAIL: CPU should be in S_FETCH2 state after reset"
			severity error;

		wait for 3 * CLK_PERIOD;
		report "Testbench complete." severity note;
		sim_done <= true;
		wait;
	end process stimulus;

end sim;

bootcamp/week5/exercise_1/out.vcd
$date
  Tue Jul 21 21:06:32 2026
$end
$version
  GHDL v0
$end
$timescale
  1 fs
$end
$scope module standard $end
$upscope $end
$scope module std_logic_1164 $end
$upscope $end
$scope module numeric_std $end
$upscope $end
$scope module tb_mini_cpu_ex1 $end
$var reg 1 ! clk $end
$var reg 1 " reset $end
$var reg 1 # done $end
$var reg 8 $ dbg_acc[7:0] $end
$var reg 5 % dbg_pc[4:0] $end
$var reg 8 & dbg_ir[7:0] $end
$var reg 3 ' dbg_state[2:0] $end
$var reg 1 ( sim_done $end
$scope module uut $end
$var reg 1 ) clk $end
$var reg 1 * reset $end
$var reg 1 + done $end
$var reg 8 , dbg_acc[7:0] $end
$var reg 5 - dbg_pc[4:0] $end
$var reg 8 . dbg_ir[7:0] $end
$var reg 3 / dbg_state[2:0] $end
$comment state is not handled $end
$comment next_state is not handled $end
$var reg 5 0 pc[4:0] $end
$var reg 8 1 ir[7:0] $end
$var reg 8 2 acc[7:0] $end
$var reg 3 3 ir_opcode[2:0] $end
$var reg 5 4 ir_operand[4:0] $end
$var reg 5 5 addr[4:0] $end
$var reg 8 6 alu_result[7:0] $end
$var reg 1 7 alu_zero $end
$var reg 8 8 mem_data_out[7:0] $end
$var reg 3 9 alu_op[2:0] $end
$var reg 1 : acc_ld $end
$var reg 1 ; ir_ld $end
$var reg 1 < mem_we $end
$var reg 1 = pc_inc $end
$var reg 1 > addr_sel $end
$var reg 1 ? done_int $end
$scope module ram_inst $end
$var reg 1 @ clk $end
$var reg 1 A we $end
$var reg 5 B addr[4:0] $end
$var reg 8 C data_in[7:0] $end
$var reg 8 D data_out[7:0] $end
$comment ram_mem is not handled $end
$var reg 8 E data_out_reg[7:0] $end
$upscope $end
$scope module alu_inst $end
$var reg 8 F a[7:0] $end
$var reg 8 G b[7:0] $end
$var reg 3 H op[2:0] $end
$var reg 8 I result[7:0] $end
$var reg 1 J zero $end
$var reg 8 K result_int[7:0] $end
$upscope $end
$upscope $end
$upscope $end
$enddefinitions $end
#0
1!
1"
0#
b00000000 $
b00000 %
b00000000 &
b000 '
0(
1)
1*
0+
b00000000 ,
b00000 -
b00000000 .
b000 /
b00000 0
b00000000 1
b00000000 2
b000 3
b00000 4
b00000 5
b00010000 6
07
b00010000 8
b111 9
0:
0;
0<
0=
0>
0?
1@
0A
b00000 B
b00000000 C
b00010000 D
b00010000 E
b00000000 F
b00010000 G
b111 H
b00010000 I
0J
b00010000 K
#5000000
0!
0)
0@
#10000000
1!
1)
1@
#15000000
0!
0)
0@
#20000000
1!
1)
1@
#25000000
0!
0)
0@
#30000000
1!
0"
b001 '
1)
0*
b001 /
1;
1=
1@
#35000000
0!
0)
0@
#40000000
1!
b00001 %
b00010000 &
b010 '
1)
b00001 -
b00010000 .
b010 /
b00001 0
b00010000 1
b10000 4
b10000 5
0;
0=
1>
1@
b10000 B
#45000000
0!
0)
0@
#50000000
1!
b011 '
1)
b011 /
b00001111 6
b00001111 8
1:
1@
b00001111 D
b00001111 E
b00001111 G
b00001111 I
b00001111 K
#55000000
0!
0)
0@
#60000000
1!
b00001111 $
b000 '
1)
b00001111 ,
b000 /
b00001111 2
b00001 5
0:
0>
1@
b00001 B
b00001111 C
b00001111 F
#65000000
0!
0)
0@
#70000000
1!
b001 '
1)
b001 /
b00110001 6
b00110001 8
1;
1=
1@
b00110001 D
b00110001 E
b00110001 G
b00110001 I
b00110001 K
#75000000
0!
0)
0@
#80000000
1!
b00010 %
b00110001 &
b010 '
1)
b00010 -
b00110001 .
b010 /
b00010 0
b00110001 1
b001 3
b10001 4
b10001 5
0;
0=
1>
1@
b10001 B
#85000000
0!
0)
0@
#90000000
1!
b011 '
1)
b011 /
b00011000 6
b00001001 8
b000 9
1:
1@
b00001001 D
b00001001 E
b00001001 G
b000 H
b00011000 I
b00011000 K
#95000000
0!
0)
0@
#100000000
1!
b00011000 $
b000 '
1)
b00011000 ,
b000 /
b00011000 2
b00010 5
b00001001 6
b111 9
0:
0>
1@
b00010 B
b00011000 C
b00011000 F
b111 H
b00001001 I
b00001001 K
#105000000
0!
0)
0@
#110000000
1!
b001 '
1)
b001 /
b00110010 6
b00110010 8
1;
1=
1@
b00110010 D
b00110010 E
b00110010 G
b00110010 I
b00110010 K
#115000000
0!
0)
0@
#120000000
1!
b00011 %
b00110010 &
b010 '
1)
b00011 -
b00110010 .
b010 /
b00011 0
b00110010 1
b10010 4
b10010 5
0;
0=
1>
1@
b10010 B
#125000000
0!
0)
0@
#130000000
1!
b011 '
1)
b011 /
b00010100 6
b11111100 8
b000 9
1:
1@
b11111100 D
b11111100 E
b11111100 G
b000 H
b00010100 I
b00010100 K
#135000000
0!
0)
0@
#140000000
1!
b00010100 $
b000 '
1)
b00010100 ,
b000 /
b00010100 2
b00011 5
b11111100 6
b111 9
0:
0>
1@
b00011 B
b00010100 C
b00010100 F
b111 H
b11111100 I
b11111100 K
#145000000
0!
0)
0@
#150000000
1!
b001 '
1)
b001 /
b01010011 6
b01010011 8
1;
1=
1@
b01010011 D
b01010011 E
b01010011 G
b01010011 I
b01010011 K
#155000000
0!
0)
0@
#160000000
1!
b00100 %
b01010011 &
b010 '
1)
b00100 -
b01010011 .
b010 /
b00100 0
b01010011 1
b010 3
b10011 4
b10011 5
0;
0=
1>
1@
b10011 B
#165000000
0!
0)
0@
#170000000
1!
b011 '
1)
b011 /
b00000000 6
17
b00000000 8
1<
1@
1A
b00000000 D
b00000000 E
b00000000 G
b00000000 I
1J
b00000000 K
#175000000
0!
0)
0@
#180000000
1!
b000 '
1)
b000 /
b00100 5
0<
0>
1@
0A
b00100 B
#185000000
0!
0)
0@
#190000000
1!
b001 '
1)
b001 /
b01100000 6
07
b01100000 8
1;
1=
1@
b01100000 D
b01100000 E
b01100000 G
b01100000 I
0J
b01100000 K
#195000000
0!
0)
0@
#200000000
1!
b00101 %
b01100000 &
b010 '
1)
b00101 -
b01100000 .
b010 /
b00101 0
b01100000 1
b011 3
b00000 4
b00000 5
0;
0=
1>
1@
b00000 B
#205000000
0!
0)
0@
#210000000
1!
1#
b100 '
1)
1+
b100 /
b00101 5
b00010000 6
b00010000 8
0>
1?
1@
b00101 B
b00010000 D
b00010000 E
b00010000 G
b00010000 I
b00010000 K
#215000000
0!
0)
0@
#220000000
1!
1)
b00000000 6
17
b00000000 8
1@
b00000000 D
b00000000 E
b00000000 G
b00000000 I
1J
b00000000 K
#225000000
0!
0)
0@
#230000000
1!
1)
1@
#235000000
0!
0)
0@
#240000000
1!
1)
1@
#245000000
0!
0)
0@
#250000000
1!
1)
1@
#255000000
0!
0)
0@
#260000000
1!
1)
1@
#265000000
0!
0)
0@
#270000000
1!
1"
0#
b00000000 $
b00000 %
b00000000 &
b000 '
1)
1*
0+
b00000000 ,
b00000 -
b00000000 .
b000 /
b00000 0
b00000000 1
b00000000 2
b000 3
b00000 5
0?
1@
b00000 B
b00000000 C
b00000000 F
#275000000
0!
0)
0@
#280000000
1!
1)
b00010000 6
07
b00010000 8
1@
b00010000 D
b00010000 E
b00010000 G
b00010000 I
0J
b00010000 K
#285000000
0!
0)
0@
#290000000
1!
0"
b001 '
1)
0*
b001 /
1;
1=
1@
#295000000
0!
0)
0@
#300000000
1!
b00001 %
b00010000 &
b010 '
1)
b00001 -
b00010000 .
b010 /
b00001 0
b00010000 1
b10000 4
b10000 5
0;
0=
1>
1@
b10000 B
#305000000
0!
0)
0@
#310000000
1!
b011 '
1)
b011 /
b00001111 6
b00001111 8
1:
1@
b00001111 D
b00001111 E
b00001111 G
b00001111 I
b00001111 K
#315000000
0!
0)
0@
#320000000
1!
b00001111 $
b000 '
1)
b00001111 ,
b000 /
b00001111 2
b00001 5
0:
0>
1@
b00001 B
b00001111 C
b00001111 F
#325000000
0!
0)
0@
#330000000
1!
b001 '
1(
1)
b001 /
b00110001 6
b00110001 8
1;
1=
1@
b00110001 D
b00110001 E
b00110001 G
b00110001 I
b00110001 K
