bootcamp/week1_basics/mux2_en/Gates.vhdl

library ieee;
use ieee.std_logic_1164.all;

package gates is

    component inverter is
        port (
            a : in std_logic;
            y : out std_logic
        );
    end component;

    component and_gate is
        port (
            a : in std_logic;
            b : in std_logic;
            y : out std_logic
        );
    end component;

    component nand_gate is
        port (
            a : in std_logic;
            b : in std_logic;
            y : out std_logic
        );
    end component;

    component or_gate is
        port (
            a : in std_logic;
            b : in std_logic;
            y : out std_logic
        );
    end component;

    component nor_gate is
        port (
            a : in std_logic;
            b : in std_logic;
            y : out std_logic
        );
    end component;

    component xor_gate is
        port (
            a : in std_logic;
            b : in std_logic;
            y : out std_logic
        );
    end component;

    component xnor_gate is
        port (
            a : in std_logic;
            b : in std_logic;
            y : out std_logic
        );
    end component;

    component half_adder is
        port (
            a     : in std_logic;
            b     : in std_logic;
            sum   : out std_logic;
            carry : out std_logic
        );
    end component;

end package gates;

--------------------------------------------------
-- Inverter
--------------------------------------------------

library ieee;
use ieee.std_logic_1164.all;

entity inverter is
    port (
        a : in std_logic;
        y : out std_logic
    );
end entity inverter;

architecture rtl of inverter is
begin

    y <= not a;

end rtl;

--------------------------------------------------
-- AND Gate
--------------------------------------------------

library ieee;
use ieee.std_logic_1164.all;

entity and_gate is
    port (
        a : in std_logic;
        b : in std_logic;
        y : out std_logic
    );
end entity and_gate;

architecture rtl of and_gate is
begin

    y <= a and b;

end rtl;

--------------------------------------------------
-- NAND Gate
--------------------------------------------------

library ieee;
use ieee.std_logic_1164.all;

entity nand_gate is
    port (
        a : in std_logic;
        b : in std_logic;
        y : out std_logic
    );
end entity nand_gate;

architecture rtl of nand_gate is
begin

    y <= not (a and b);

end rtl;

--------------------------------------------------
-- OR Gate
--------------------------------------------------

library ieee;
use ieee.std_logic_1164.all;

entity or_gate is
    port (
        a : in std_logic;
        b : in std_logic;
        y : out std_logic
    );
end entity or_gate;

architecture rtl of or_gate is
begin

    y <= a or b;

end rtl;

--------------------------------------------------
-- NOR Gate
--------------------------------------------------

library ieee;
use ieee.std_logic_1164.all;

entity nor_gate is
    port (
        a : in std_logic;
        b : in std_logic;
        y : out std_logic
    );
end entity nor_gate;

architecture rtl of nor_gate is
begin

    y <= not (a or b);

end rtl;

--------------------------------------------------
-- XOR Gate
--------------------------------------------------

library ieee;
use ieee.std_logic_1164.all;

entity xor_gate is
    port (
        a : in std_logic;
        b : in std_logic;
        y : out std_logic
    );
end entity xor_gate;

architecture rtl of xor_gate is
begin

    y <= a xor b;

end rtl;

--------------------------------------------------
-- XNOR Gate
--------------------------------------------------

library ieee;
use ieee.std_logic_1164.all;

entity xnor_gate is
    port (
        a : in std_logic;
        b : in std_logic;
        y : out std_logic
    );
end entity xnor_gate;

architecture rtl of xnor_gate is
begin

    y <= not (a xor b);

end rtl;

--------------------------------------------------
-- Half Adder
--------------------------------------------------

library ieee;
use ieee.std_logic_1164.all;

entity half_adder is
    port (
        a     : in std_logic;
        b     : in std_logic;
        sum   : out std_logic;
        carry : out std_logic
    );
end entity half_adder;

architecture rtl of half_adder is
begin

    sum   <= a xor b;
    carry <= a and b;

end rtl;

bootcamp/week1_basics/mux2_en/mux2_en.vhdl
library ieee;
use ieee.std_logic_1164.all;

library work;
use work.gates.all;

entity mux2_en is
   port (a, b, sel, en: in std_logic;
   y: out std_logic);
end mux2_en;

architecture switch of mux2_en is
   signal not_sel, a_and, b_and, checken: std_logic;
   begin
      unsel: entity work.inverter
         port map (a=>sel, y=>not_sel);

      asel: entity work.and_gate
         port map (a=>a, b=>not_sel, y=>a_and);

      bsel: entity work.and_gate
         port map (a=>sel, b=>b, y=>b_and);

      almost: entity work.or_gate
         port map (a=>a_and, b=>b_and, y=>checken);

      there: entity work.and_gate
         port map (a=>en, b=>checken, y=>y);
end switch;

bootcamp/week1_basics/mux2_en/tb_mux2_en.vhd
-- tb_mux2.vhd
-- Week 1 PROVIDED testbench for Exercise 2 (2:1 multiplexer).
--
-- You build the entity 'mux2' with ports a, b, sel, y.
-- Behaviour: sel='0' -> y follows a ; sel='1' -> y follows b.
--
-- Distinct values are placed on a and b so you can clearly SEE
-- which input is being routed to y in the waveform.

library IEEE;
use IEEE.STD_LOGIC_1164.ALL;

entity tb_mux2_en is
end tb_mux2_en;

architecture sim of tb_mux2_en is

    signal a, b, sel, y, en : std_logic;

begin

    uut : entity work.mux2_en
        port map (
            a   => a,
            b   => b,
            sel => sel,
            y   => y,
            en  => en
        );

    stimulus : process
    begin
        a <= '0'; b <= '0'; sel <= '0'; en <= '0';
        wait for 10 ns;
  
        a <= '0'; b <= '0'; sel <= '1'; en <= '0';
        wait for 10 ns;
  
        a <= '0'; b <= '1'; sel <= '0'; en <= '0';
        wait for 10 ns;
  
        a <= '0'; b <= '1'; sel <= '1'; en <= '0';
        wait for 10 ns;
  
        a <= '1'; b <= '0'; sel <= '0'; en <= '0';
        wait for 10 ns;
  
        a <= '1'; b <= '0'; sel <= '1'; en <= '0';
        wait for 10 ns;
  
        a <= '1'; b <= '1'; sel <= '0'; en <= '0';
        wait for 10 ns;
  
        a <= '1'; b <= '1'; sel <= '1'; en <= '0';
        wait for 10 ns;

        a <= '0'; b <= '0'; sel <= '0'; en <= '1';
        wait for 10 ns;
  
        a <= '0'; b <= '0'; sel <= '1'; en <= '1';
        wait for 10 ns;
  
        a <= '0'; b <= '1'; sel <= '0'; en <= '1';
        wait for 10 ns;
  
        a <= '0'; b <= '1'; sel <= '1'; en <= '1';
        wait for 10 ns;
  
        a <= '1'; b <= '0'; sel <= '0'; en <= '1';
        wait for 10 ns;
  
        a <= '1'; b <= '0'; sel <= '1'; en <= '1';
        wait for 10 ns;
  
        a <= '1'; b <= '1'; sel <= '0'; en <= '1';
        wait for 10 ns;
  
        a <= '1'; b <= '1'; sel <= '1'; en <= '1';
        wait for 10 ns;

        wait;
    end process;

end sim;

bootcamp/week1_basics/mux2_en/out.vcd
$date
  Thu May 28 17:27:19 2026
$end
$version
  GHDL v0
$end
$timescale
  1 fs
$end
$scope module standard $end
$upscope $end
$scope module std_logic_1164 $end
$upscope $end
$scope module gates $end
$upscope $end
$scope module tb_mux2_en $end
$var reg 1 ! a $end
$var reg 1 " b $end
$var reg 1 # sel $end
$var reg 1 $ y $end
$var reg 1 % en $end
$scope module uut $end
$var reg 1 & a $end
$var reg 1 ' b $end
$var reg 1 ( sel $end
$var reg 1 ) en $end
$var reg 1 * y $end
$var reg 1 + not_sel $end
$var reg 1 , a_and $end
$var reg 1 - b_and $end
$var reg 1 . checken $end
$scope module unsel $end
$var reg 1 / a $end
$var reg 1 0 y $end
$upscope $end
$scope module asel $end
$var reg 1 1 a $end
$var reg 1 2 b $end
$var reg 1 3 y $end
$upscope $end
$scope module bsel $end
$var reg 1 4 a $end
$var reg 1 5 b $end
$var reg 1 6 y $end
$upscope $end
$scope module almost $end
$var reg 1 7 a $end
$var reg 1 8 b $end
$var reg 1 9 y $end
$upscope $end
$scope module there $end
$var reg 1 : a $end
$var reg 1 ; b $end
$var reg 1 < y $end
$upscope $end
$upscope $end
$upscope $end
$enddefinitions $end
#0
0!
0"
0#
0$
0%
0&
0'
0(
0)
0*
1+
0,
0-
0.
0/
10
01
12
03
04
05
06
07
08
09
0:
0;
0<
#10000000
1#
1(
0+
1/
00
02
14
#20000000
1"
0#
1'
0(
1+
0/
10
12
04
15
#30000000
1#
1(
0+
1-
1.
1/
00
02
14
16
18
19
1;
#40000000
1!
0"
0#
1&
0'
0(
1+
1,
0-
1.
0/
10
11
12
13
04
05
06
17
08
19
1;
#50000000
1#
1(
0+
0,
0.
1/
00
02
03
14
07
09
0;
#60000000
1"
0#
1'
0(
1+
1,
1.
0/
10
12
13
04
15
17
19
1;
#70000000
1#
1(
0+
0,
1-
1/
00
02
03
14
16
07
18
#80000000
0!
0"
0#
0$
1%
0&
0'
0(
1)
0*
1+
0-
0.
0/
10
01
12
04
05
06
08
09
1:
0;
0<
#90000000
1#
1(
0+
1/
00
02
14
#100000000
1"
0#
1'
0(
1+
0/
10
12
04
15
#110000000
1#
1$
1(
1*
0+
1-
1.
1/
00
02
14
16
18
19
1;
1<
#120000000
1!
0"
0#
1$
1&
0'
0(
1*
1+
1,
0-
1.
0/
10
11
12
13
04
05
06
17
08
19
1;
1<
#130000000
1#
0$
1(
0*
0+
0,
0.
1/
00
02
03
14
07
09
0;
0<
#140000000
1"
0#
1$
1'
0(
1*
1+
1,
1.
0/
10
12
13
04
15
17
19
1;
1<
#150000000
1#
1(
0+
0,
1-
1/
00
02
03
14
16
07
18
